Workbook

Sheet Read_Me
A1: HUL Financial Performance & Forecasting
A3: Company | B3: Hindustan Unilever Limited
A4: Project period | B4: FY2014–15 to FY2024–25
A5: Tool | B5: Microsoft Excel
A6: Project focus | B6: Financial performance analysis and forecasting
A7: Career relevance | B7: Financial Analyst / FP&A
A9: Main objective | B9: Analyze historical financial performance and estimate future performance using transparent assumptions.
A10: Important limitation | B10: Forecasts are model estimates, not company guidance or guaranteed results.

Sheet Historical_Data
A1: Financial Year | B1: Turnover (₹ crore) | C1: EBITDA (₹ crore) | D1: PAT (₹ crore)
A2: 2015–16 | B2: 33891 | C2: 6013 | D2: 4158
A3: 2016–17 | B3: 35061 | C3: 6328 | D3: 4502
A4: 2017–18 | B4: 35571 | C4: 7501 | D4: 5225
A5: 2018–19 | B5: 38684 | C5: 8880 | D5: 6060
A6: 2019–20 | B6: 39238 | C6: 9853 | D6: 6764
A7: 2020–21 | B7: 46321 | C7: 11625 | D7: 8000
A8: 2021–22 | B8: 51548 | C8: 12862 | D8: 8887
A9: 2022–23 | B9: 59549 | C9: 14148 | D9: 10144
A10: 2023–24 | B10: 60966 | C10: 14663 | D10: 10282
A11: 2024–25 | B11: 60573 | C11: 14706 | D11: 10680
A12: 2025–26 | B12: 63763 | C12: 15054 | D12: 10652

Sheet Financial_Analysis
A1: Financial Year | B1: Turnover (₹ crore) | C1: EBITDA (₹ crore) | D1: PAT (₹ crore) | E1: Turnover Growth % | F1: EBITDA Growth % | G1: PAT Growth % | H1: EBITDA Margin % | I1: PAT Margin %
A2: 2015–16 | B2: 33891 | C2: 6013 | D2: 4158 | H2: =C2/B2 -> 0.17742173 | I2: =D2/B2 -> 0.12268744 | K2: Financial KPI | L2: Value | M2: Analysis Area | N2: Interpretation
A3: 2016–17 | B3: 35061 | C3: 6328 | D3: 4502 | E3: =B3/B2-1 -> 0.03452244 | F3: =(C3/C2)-1 -> 0.052386496 | G3: =(D3/D2)-1 -> 0.082732083 | H3: =C3/B3 -> 0.18048544 | I3: =D3/B3 -> 0.12840478 | K3: Latest Turnover | L3: =B12 -> 63763 | M3: Revenue Trend | N3: Turnover increased from ₹33,891 crore in FY2015-16 to ₹63,763 crore in FY2025-26, indicating substantial long-term expansion.
A4: 2017–18 | B4: 35571 | C4: 7501 | D4: 5225 | E4: =B4/B3-1 -> 0.014546077 | F4: =(C4/C3)-1 -> 0.18536662 | G4: =(D4/D3)-1 -> 0.16059529 | H4: =C4/B4 -> 0.21087403 | I4: =D4/B4 -> 0.14688932 | K4: Latest EBITDA | L4: =C12 -> 15054 | M4: EBITDA Trend | N4: EBITDA increased from ₹5,749 crore to ₹15,054 crore over the same period, indicating growth in operating earnings.
A5: 2018–19 | B5: 38684 | C5: 8880 | D5: 6060 | E5: =B5/B4-1 -> 0.087515111 | F5: =(C5/C4)-1 -> 0.18384215 | G5: =(D5/D4)-1 -> 0.15980861 | H5: =C5/B5 -> 0.22955227 | I5: =D5/B5 -> 0.15665391 | K5: Latest PAT | L5: =D12 -> 10652 | M5: PAT Trend | N5: Reported PAT increased from ₹4,137 crore to ₹10,652 crore across the period.
A6: 2019–20 | B6: 39238 | C6: 9853 | D6: 6764 | E6: =B6/B5-1 -> 0.014321166 | F6: =(C6/C5)-1 -> 0.10957207 | G6: =(D6/D5)-1 -> 0.11617162 | H6: =C6/B6 -> 0.25110862 | I6: =D6/B6 -> 0.17238391 | K6: Latest EBITDA Margin | L6: =H12 -> 0.23609303 | M6: Profitability | N6: EBITDA and PAT margins show how efficiently turnover is converted into operating earnings and reported profit.
A7: 2020–21 | B7: 46321 | C7: 11625 | D7: 8000 | E7: =B7/B6-1 -> 0.18051379 | F7: =(C7/C6)-1 -> 0.1798437 | G7: =(D7/D6)-1 -> 0.18273211 | H7: =C7/B7 -> 0.25096608 | I7: =D7/B7 -> 0.17270784 | K7: Latest PAT Margin | L7: =I12 -> 0.16705613 | M7: Recent Performance | N7: Turnover declined in FY2024-25 relative to FY2023-24 before increasing in FY2025-26. Review annual reports for business context.
A8: 2021–22 | B8: 51548 | C8: 12862 | D8: 8887 | E8: =B8/B7-1 -> 0.11284299 | F8: =(C8/C7)-1 -> 0.1064086 | G8: =(D8/D7)-1 -> 0.110875 | H8: =C8/B8 -> 0.24951502 | I8: =D8/B8 -> 0.17240242 | K8: Turnover CAGR | L8: =(B12/B2)^(1/10)-1 -> 0.065242379 | M8: Forecast Implication | N8: Historical growth and margins can provide a starting point for planning, but past performance does not guarantee future results.
A9: 2022–23 | B9: 59549 | C9: 14148 | D9: 10144 | E9: =B9/B8-1 -> 0.15521456 | F9: =(C9/C8)-1 -> 0.09998445 | G9: =(D9/D8)-1 -> 0.14144256 | H9: =C9/B9 -> 0.23758585 | I9: =D9/B9 -> 0.17034711 | K9: EBITDA CAGR | L9: =(C12/C2)^(1/10)-1 -> 0.096114873 | M9: Limitation | N9: This analysis is a simplified historical trend study and does not independently adjust for all accounting, portfolio or exceptional-item changes.
A10: 2023–24 | B10: 60966 | C10: 14663 | D10: 10282 | E10: =B10/B9-1 -> 0.02379553 | F10: =(C10/C9)-1 -> 0.036400905 | G10: =(D10/D9)-1 -> 0.013604101 | H10: =C10/B10 -> 0.2405111 | I10: =D10/B10 -> 0.16865138 | K10: PAT CAGR | L10: =(D12/D2)^(1/10)-1 -> 0.098638129
A11: 2024–25 | B11: 60573 | C11: 14706 | D11: 10680 | E11: =B11/B10-1 -> -0.0064462159 | F11: =(C11/C10)-1 -> 0.0029325513 | G11: =(D11/D10)-1 -> 0.038708422 | H11: =C11/B11 -> 0.24278144 | I11: =D11/B11 -> 0.17631618 | K11: Highest Turnover Growth | L11: =MAX(E3:E12) -> 0.18051379
A12: 2025–26 | B12: 63763 | C12: 15054 | D12: 10652 | E12: =B12/B11-1 -> 0.052663728 | F12: =(C12/C11)-1 -> 0.023663811 | G12: =(D12/D11)-1 -> -0.0026217228 | H12: =C12/B12 -> 0.23609303 | I12: =D12/B12 -> 0.16705613 | K12: Lowest Turnover Growth | L12: =MIN(E3:E12) -> -0.0064462159
A13: FY2026-27 (Forecast) | B13: =Forecast!B12 -> 65251.081 | K13: Average Turnover Growth | L13: =AVERAGE(E3:E12) -> 0.066948917
K14: Average EBITDA Margin | L14: =AVERAGE(H2:H12) -> 0.22789951
K15: Average PAT Margin | L15: =AVERAGE(I2:I12) -> 0.15950004

Sheet Forecast
A1: HUL FINANCIAL FORECAST
A2: Forecast Year | B2: FY2026-27
A3: Forecast Method | B3: Recent 3-year average growth and margins
A5: ASSUMPTIONS
A6: Average Turnover Growth | B6: =AVERAGE(Financial_Analysis!E10:E12) -> 0.023337681
A7: Average EBITDA Margin | B7: =AVERAGE(Financial_Analysis!H10:H12) -> 0.23979519
A8: Average PAT Margin | B8: =AVERAGE(Financial_Analysis!I10:I12) -> 0.17067456
A10: FORECAST RESULTS
A11: Latest Actual Turnover | B11: =Historical_Data!B12 -> 63763
A12: Forecast Turnover | B12: =B11*(1+B6) -> 65251.081
A13: Latest Actual EBITDA | B13: =Historical_Data!C12 -> 15054
A14: Forecast EBITDA | B14: =B12*B7 -> 15646.895
A15: Latest Actual PAT | B15: =Historical_Data!D12 -> 10652
A16: Forecast PAT | B16: =B12*B8 -> 11136.7
A17: Forecast EBITDA Margin | B17: =B14/B12 -> 0.23979519
A18: Forecast PAT Margin | B18: =B16/B12 -> 0.17067456
A19: Forecast Turnover Growth | B19: =B12/B11-1 -> 0.023337681
A22: Forecast Interpretation | B22: Explanation
A23: Turnover | B23: Estimated by applying the average of the latest three annual turnover growth observations to the latest actual turnover.
A24: EBITDA | B24: Estimated by applying the recent average EBITDA margin to forecast turnover.
A25: PAT | B25: Estimated by applying the recent average PAT margin to forecast turnover.
A26: Limitation | B26: The model assumes recent historical trends continue. Actual results may differ because of demand, pricing, costs, taxes, acquisitions, disposals and exceptional items.

Sheet Dashboard
A37: Key Insight 1 | B37: HUL's turnover increased over the historical period.
A38: Key Insight 2 | B38: EBITDA increased over the period, while margins help evaluate the efficiency of operating earnings.
A39: Key Insight 3 | B39: The forecast uses recent historical growth and margin assumptions rather than company guidance.
A40: Important Note | B40: All financial values are in ₹ crore. The FY2026-27 figures are illustrative estimates, not actual results.

Sheet Sources
A1: Source ID | B1: Source / Reference | C1: Purpose | D1: URL
A2: S1 | B2: HUL Financial Performance FY2025-26 | C2: Historical turnover, latest EBITDA and PAT, management commentary | D2: https://hul-performance-highlights.hul.co.in/performance-highlights-fy-2025-2026/performance/financial/
A3: S2 | B3: HUL Financial Performance FY2024-25 | C3: Historical EBITDA and PAT series; prior-year comparison | D3: https://hul-performance-highlights.hul.co.in/performance-highlights-fy-2024-2025/financial-performance.html
A4: S3 | B4: HUL Annual Reports and Performance Highlights | C4: Official annual reports and financial statements | D4: https://www.hul.co.in/investors/annual-reports-and-performance-highlights/
A5: S4 | B5: HUL FY2025-26 Annual Report | C5: Financial results and supporting disclosures | D5: https://www.hul.co.in/files/annual-report-2025-26.pdf
A6: S5 | B6: Excel Financial Analysis Methodology | C6: Growth rates, margins, CAGR and historical-average forecast | D6: Calculated in this project
A9: Methodology Item | B9: Description
A10: Data Type | B10: Secondary financial data published by the company.
A11: Currency | B11: Indian rupees, expressed in crore.
A12: Turnover Growth | B12: (Current year turnover / Previous year turnover) - 1.
A13: EBITDA Growth | B13: (Current year EBITDA / Previous year EBITDA) - 1.
A14: PAT Growth | B14: (Current year PAT / Previous year PAT) - 1.
A15: EBITDA Margin | B15: EBITDA / Turnover.
A16: PAT Margin | B16: PAT / Turnover.
A17: CAGR | B17: (Ending value / Beginning value)^(1 / Number of annual intervals) - 1.
A18: Forecast Method | B18: Average of the three latest annual growth observations and average of the three latest margins.
A19: Limitations | B19: Historical definitions and discontinued operations may affect comparisons; a simplified forecast does not model every business driver.
